clinacl.py
setup.py
clinacl.egg-info/PKG-INFO
clinacl.egg-info/SOURCES.txt
clinacl.egg-info/dependency_links.txt
clinacl.egg-info/entry_points.txt
clinacl.egg-info/requires.txt
clinacl.egg-info/top_level.txt