Metadata-Version: 1.0
Name: clinacl
Version: 0.1.0
Summary: A command line tool for playing with NaCl
Home-page: https://github.com/oconnor663/clinacl
Author: Jack O'Connor <oconnor663@gmail.com>
Author-email: UNKNOWN
License: MIT
Platform: UNKNOWN
